carefree_pyo3-0.2.2.dist-info/METADATA
carefree_pyo3-0.2.2.dist-info/WHEEL
carefree_pyo3-0.2.2.dist-info/licenses/LICENSE
cfpyo3/__init__.py
cfpyo3/_rs/__init__.pyi
cfpyo3/_rs/df/__init__.pyi
cfpyo3/_rs/df/py.typed
cfpyo3/_rs/py.typed
cfpyo3/_rs/toolkit/array.pyi
cfpyo3/_rs/toolkit/misc.pyi
cfpyo3/_rs/toolkit/py.typed
cfpyo3/cfpyo3.abi3.so
cfpyo3/cfpyo3.pyi
cfpyo3/df/__init__.py
cfpyo3/df/frame.py
cfpyo3/df/utils.py
cfpyo3/py.typed
cfpyo3/toolkit/__init__.py
cfpyo3/toolkit/array.py
cfpyo3/toolkit/misc.py
carefree_pyo3-0.2.2.dist-info/RECORD
