Metadata-Version: 2.4
Name: carefree-pyo3
Version: 0.2.2
Classifier: Programming Language :: Rust
Classifier: Programming Language :: Python :: Implementation :: CPython
Requires-Dist: numpy>=1.26.4
Requires-Dist: pandas
Requires-Dist: pydantic
License-File: LICENSE
License-File: LICENSE
Summary: rust → python made easy
Keywords: rust,python,numpy,pandas
Home-Page: https://github.com/carefree0910/carefree-pyo3
Author: carefree0910 <syameimaru.saki@gmail.com>
Author-email: carefree0910 <syameimaru.saki@gmail.com>
Requires-Python: >=3.8
Project-URL: Homepage, https://github.com/carefree0910/carefree-pyo3
